Metadata-Version: 1.0
Name: sugarcrm-cloud-python
Version: 0.1.0
Summary: API wrapper for SugarCRM cloud written in Python
Home-page: https://github.com/GearPlug/sugarcrm-cloud-python
Author: Miguel Ferrer
Author-email: ingferrermiguel@gmail.com
License: MIT
Platform: UNKNOWN
